wallex_cacher/__init__.py
wallex_cacher/cacher.py
wallex_cacher/exceptions.py
wallex_cacher-0.0.2.dist-info/METADATA
wallex_cacher-0.0.2.dist-info/WHEEL
wallex_cacher-0.0.2.dist-info/top_level.txt
wallex_cacher-0.0.2.dist-info/RECORD
