Metadata-Version: 2.1
Name: wallex-cacher
Version: 0.0.2
Summary: Wallex Orderbook Cacher
Home-page: https://github.com/amiwrpremium/wallex_cacher
Author: amiwrpremium
Author-email: amiwrpremium@gmail.com
License: MIT
Project-URL: Bug Tracker, https://github.com/amiwrpremium/wallex_cacher/issues
Keywords: wallex,crypto,exchange,API,SDK,Cacher
Platform: UNKNOWN
Classifier: Development Status :: 3 - Alpha
Classifier: Intended Audience :: Developers
Classifier: Topic :: Software Development :: Build Tools
Classifier: License :: OSI Approved :: MIT License
Classifier: Programming Language :: Python :: 3
Classifier: Programming Language :: Python :: 3.4
Classifier: Programming Language :: Python :: 3.5
Classifier: Programming Language :: Python :: 3.6
Classifier: Programming Language :: Python :: 3.7
Classifier: Programming Language :: Python :: 3.8
Classifier: Programming Language :: Python :: 3.9
Requires-Python: >=3.6
Requires-Dist: requests
Requires-Dist: simplejson
Requires-Dist: wallex
